infraform/__init__.py
infraform/filters.py
infraform/list.py
infraform/show.py
infraform/utils.py
infraform/cli/__init__.py
infraform/cli/main.py
infraform/cli/parser.py
infraform/cli/utils.py
infraform/cli/list/__init__.py
infraform/cli/list/cli.py
infraform/cli/list/parser.py
infraform/cli/run/__init__.py
infraform/cli/run/cli.py
infraform/cli/run/parser.py
infraform/cli/show/__init__.py
infraform/cli/show/cli.py
infraform/cli/show/parser.py
infraform/exceptions/__init__.py
infraform/exceptions/requirements.py
infraform/exceptions/usage.py
infraform/exceptions/utils.py
infraform/platforms/__init__.py
infraform/platforms/container.py
infraform/platforms/docker.py
infraform/platforms/docker_compose.py
infraform/platforms/platform.py
infraform/platforms/podman.py
infraform/platforms/python.py
infraform/platforms/shell.py
infraform/platforms/terraform.py
infraform/scenarios/docker-compose/elk_filebeat_jenkins/docker-compose.yml
infraform/scenarios/docker-compose/elk_filebeat_jenkins/elk_filebeat_jenkins.yml
infraform/scenarios/docker-compose/elk_filebeat_jenkins/config/elasticsearch.yml
infraform/scenarios/docker-compose/elk_filebeat_jenkins/config/filebeat.yml
infraform/scenarios/docker-compose/elk_filebeat_jenkins/config/kibana.yml
infraform/scenarios/docker-compose/elk_filebeat_jenkins/config/logstash.conf
infraform/scenarios/podman/neutron-pep8-tests.yml.j2
infraform/scenarios/podman/pep8-tests.yml.j2
infraform/scenarios/podman/rhel7-pep8-tests.yml.j2
infraform/scenarios/podman/rhel7-unit-tests.yml.j2
infraform/scenarios/podman/unit-tests.yml.j2
infraform/scenarios/python/elastic_summary.py.j2
infraform/scenarios/shell/install-minikube.sh
infraform/scenarios/shell/register-jenkins-node.sh.j2
infraform/scenarios/shell/setup-jenkins-node.sh.j2
infraform/scenarios/terraform/libvirt-1-vm.tf.j2
infraform/scenarios/terraform/os-1-vm-fip.tf.j2
infraform-0.1.dist-info/LICENSE
infraform-0.1.dist-info/METADATA
infraform-0.1.dist-info/WHEEL
infraform-0.1.dist-info/entry_points.txt
infraform-0.1.dist-info/top_level.txt
infraform-0.1.dist-info/RECORD
