Metadata-Version: 2.1
Name: infraform
Version: 0.1
Summary: Creating the infra you need, not the one you want
Home-page: UNKNOWN
Author: Arie Bregman
Author-email: abregman@redhat.com
License: UNKNOWN
Platform: UNKNOWN
Requires-Python: >3.0.0
